Lab00/Ejercicio1_FSM_Semaforo_Simple/semaforo.v
module semaforo(
    input  clk,
    input  reset,
    output reg [1:0] luz   // 2 bits: 00=verde, 01=amarillo, 10=rojo
);
    localparam verde    = 2'b00;
    localparam amarillo = 2'b01;
    localparam rojo     = 2'b10;

    reg [3:0] cont;
    reg [1:0] state;

    always @(posedge clk) begin
        if (reset) begin
            state <= verde;
            cont  <= 1;
        end
        else begin
            cont <= cont + 1;

            if (cont < 5) begin
                state <= verde;
            end
            else if (cont == 5) begin
                state <= amarillo;
            end
            else if (cont == 7) begin
                state <= rojo;
            end
            else if (cont == 11) begin
                state <= amarillo;
            end
            else if (cont == 13) begin
                state <= verde;
                cont<=1;
            end
        end
    end

    always @(*) begin
        luz = state;
    end

endmodule

Lab00/Ejercicio1_FSM_Semaforo_Simple/tb_semaforo.v
`timescale 1ns/1ns
`include "semaforo.v"

module tb_semaforo;

  reg  clk, reset;
  wire [1:0] luz;

  semaforo dut (
    .clk(clk),
    .reset(reset),
    .luz(luz)
  );

  always #5 clk = ~clk;

  initial begin
    $dumpfile("semaforo.vcd");
    $dumpvars(0, tb_semaforo);

    clk   = 0;
    reset = 1;
    #12 reset = 0;
    #400 $finish; 
  end

endmodule

Lab00/Ejercicio1_FSM_Semaforo_Simple/semaforo.vcd
$date
	Fri Sep 11 14:47:15 2026
$end
$version
	Icarus Verilog
$end
$timescale
	1ns
$end
$scope module tb_semaforo $end
$var wire 2 ! luz [1:0] $end
$var reg 1 " clk $end
$var reg 1 # reset $end
$scope module dut $end
$var wire 1 " clk $end
$var wire 1 # reset $end
$var parameter 2 $ amarillo $end
$var parameter 2 % rojo $end
$var parameter 2 & verde $end
$var reg 4 ' cont [3:0] $end
$var reg 2 ( luz [1:0] $end
$var reg 2 ) state [1:0] $end
$upscope $end
$upscope $end
$enddefinitions $end
$comment Show the parameter values. $end
$dumpall
b0 &
b10 %
b1 $
$end
#0
$dumpvars
bx )
bx (
bx '
1#
0"
bx !
$end
#5
b0 !
b0 (
b1 '
b0 )
1"
#10
0"
#12
0#
#15
b10 '
1"
#20
0"
#25
b11 '
1"
#30
0"
#35
b100 '
1"
#40
0"
#45
b101 '
1"
#50
0"
#55
b1 !
b1 (
b1 )
b110 '
1"
#60
0"
#65
b111 '
1"
#70
0"
#75
b10 !
b10 (
b10 )
b1000 '
1"
#80
0"
#85
b1001 '
1"
#90
0"
#95
b1010 '
1"
#100
0"
#105
b1011 '
1"
#110
0"
#115
b1 !
b1 (
b1 )
b1100 '
1"
#120
0"
#125
b1101 '
1"
#130
0"
#135
b0 !
b0 (
b0 )
b1 '
1"
#140
0"
#145
b10 '
1"
#150
0"
#155
b11 '
1"
#160
0"
#165
b100 '
1"
#170
0"
#175
b101 '
1"
#180
0"
#185
b1 !
b1 (
b1 )
b110 '
1"
#190
0"
#195
b111 '
1"
#200
0"
#205
b10 !
b10 (
b10 )
b1000 '
1"
#210
0"
#215
b1001 '
1"
#220
0"
#225
b1010 '
1"
#230
0"
#235
b1011 '
1"
#240
0"
#245
b1 !
b1 (
b1 )
b1100 '
1"
#250
0"
#255
b1101 '
1"
#260
0"
#265
b0 !
b0 (
b0 )
b1 '
1"
#270
0"
#275
b10 '
1"
#280
0"
#285
b11 '
1"
#290
0"
#295
b100 '
1"
#300
0"
#305
b101 '
1"
#310
0"
#315
b1 !
b1 (
b1 )
b110 '
1"
#320
0"
#325
b111 '
1"
#330
0"
#335
b10 !
b10 (
b10 )
b1000 '
1"
#340
0"
#345
b1001 '
1"
#350
0"
#355
b1010 '
1"
#360
0"
#365
b1011 '
1"
#370
0"
#375
b1 !
b1 (
b1 )
b1100 '
1"
#380
0"
#385
b1101 '
1"
#390
0"
#395
b0 !
b0 (
b0 )
b1 '
1"
#400
0"
#405
b10 '
1"
