Verilog/acumulador.v
module acumulador(
    input  clk,
    input  start,
    input  reset,
    input  cancel,
    input  [1:0] group,
    input  [3:0] x,
    output reg [5:0] acc
);
    reg [4:0] cont;
    reg [1:0] state; //idle=00 load=01 add=11 done=10
    localparam idle = 2'b00;
    localparam load = 2'b01;
    localparam add  = 2'b11;
    localparam done = 2'b10;

    always @(posedge clk) begin
        if (reset) begin
            state <= idle;
            cont  <= 0;
            acc   <= 0;
        end
        else begin
            if (state==idle && start && !cancel) begin
                state <= load;
            end
            else if (state==load && cancel) begin
                state <= idle;
            end
            else if (state==load && !cancel) begin
                acc   <= 0;
                cont  <= 0;
                state <= add;
            end
            else if (state==add && cancel) begin
                state <= idle;
            end
            else if (state==add && group==2'b00 && !cancel) begin //group=00 -> sumar 3 veces
                if (cont < 3) begin
                    acc  <= acc + x;
                    cont <= cont + 1;
                end
                else begin
                    state <= done;
                end
            end
            else if (state==add && group==2'b01 && !cancel) begin //group=01 -> sumar 4 veces
                if (cont < 4) begin
                    acc  <= acc + x;
                    cont <= cont + 1;
                end
                else begin
                    state <= done;
                end
            end
            else if (state==add && group==2'b11 && !cancel) begin //group=11 -> sumar hasta acc>=20
                if (acc < 20) begin
                    acc <= acc + x;
                end
                else begin
                    state <= done;
                end
            end
            else if (state==done) begin
                state <= idle;
            end
        end
    end
endmodule

Lab00/Ejercicio2_Acumulador_Secuencial/tb_acumulador.v
`timescale 1ns/1ns
`include "acumulador.v"

module tb_acumulador;

  reg        clk, reset, start, cancel;
  reg  [1:0] group;
  reg  [3:0] x;
  wire [5:0] acc;

  acumulador dut (
    .clk(clk),
    .start(start),
    .reset(reset),
    .cancel(cancel),
    .group(group),
    .x(x),
    .acc(acc)
  );

  always #5 clk = ~clk;

  initial begin
    $dumpfile("acumulador.vcd");
    $dumpvars(0, tb_acumulador);

    clk    = 0;
    reset  = 1;
    start  = 0;
    cancel = 0;
    group  = 2'b00;
    x      = 4'd0;

    #12 reset = 0;

    // ---- Caso 1: group=00 -> sumar x 3 veces ----
    x     = 4'd5;
    group = 2'b00;
    #10 start = 1;
    #10 start = 0;
    #60;

    // ---- Caso 2: group=01 -> sumar x 4 veces ----
    x     = 4'd3;
    group = 2'b01;
    #10 start = 1;
    #10 start = 0;
    #70;

    // ---- Caso 3: group=11 -> sumar hasta acc>=20 ----
    x     = 4'd7;
    group = 2'b11;
    #10 start = 1;
    #10 start = 0;
    #80;

    // ---- Caso 4: cancelar a mitad de la acumulacion ----
    x     = 4'd2;
    group = 2'b00;
    #10 start  = 1;
    #10 start  = 0;
    #15 cancel = 1; 
    #10 cancel = 0;
    #40;

    #20 $finish;
  end

endmodule

Lab00/Ejercicio2_Acumulador_Secuencial/acumulador.vcd
$date
	Fri Sep 18 14:36:04 2026
$end
$version
	Icarus Verilog
$end
$timescale
	1ns
$end
$scope module tb_acumulador $end
$var wire 6 ! acc [5:0] $end
$var reg 1 " cancel $end
$var reg 1 # clk $end
$var reg 2 $ group [1:0] $end
$var reg 1 % reset $end
$var reg 1 & start $end
$var reg 4 ' x [3:0] $end
$scope module dut $end
$var wire 1 " cancel $end
$var wire 1 # clk $end
$var wire 2 ( group [1:0] $end
$var wire 1 % reset $end
$var wire 1 & start $end
$var wire 4 ) x [3:0] $end
$var parameter 2 * add $end
$var parameter 2 + done $end
$var parameter 2 , idle $end
$var parameter 2 - load $end
$var reg 6 . acc [5:0] $end
$var reg 5 / cont [4:0] $end
$var reg 2 0 state [1:0] $end
$upscope $end
$upscope $end
$enddefinitions $end
$comment Show the parameter values. $end
$dumpall
b1 -
b0 ,
b10 +
b11 *
$end
#0
$dumpvars
bx 0
bx /
bx .
b0 )
b0 (
b0 '
0&
1%
b0 $
0#
0"
bx !
$end
#5
b0 !
b0 .
b0 /
b0 0
1#
#10
0#
#12
b101 '
b101 )
0%
#15
1#
#20
0#
#22
1&
#25
b1 0
1#
#30
0#
#32
0&
#35
b11 0
1#
#40
0#
#45
b1 /
b101 !
b101 .
1#
#50
0#
#55
b10 /
b1010 !
b1010 .
1#
#60
0#
#65
b11 /
b1111 !
b1111 .
1#
#70
0#
#75
b10 0
1#
#80
0#
#85
b0 0
1#
#90
0#
#92
b1 $
b1 (
b11 '
b11 )
#95
1#
#100
0#
#102
1&
#105
b1 0
1#
#110
0#
#112
0&
#115
b11 0
b0 /
b0 !
b0 .
1#
#120
0#
#125
b1 /
b11 !
b11 .
1#
#130
0#
#135
b10 /
b110 !
b110 .
1#
#140
0#
#145
b11 /
b1001 !
b1001 .
1#
#150
0#
#155
b100 /
b1100 !
b1100 .
1#
#160
0#
#165
b10 0
1#
#170
0#
#175
b0 0
1#
#180
0#
#182
b11 $
b11 (
b111 '
b111 )
#185
1#
#190
0#
#192
1&
#195
b1 0
1#
#200
0#
#202
0&
#205
b11 0
b0 /
b0 !
b0 .
1#
#210
0#
#215
b111 !
b111 .
1#
#220
0#
#225
b1110 !
b1110 .
1#
#230
0#
#235
b10101 !
b10101 .
1#
#240
0#
#245
b10 0
1#
#250
0#
#255
b0 0
1#
#260
0#
#265
1#
#270
0#
#275
1#
#280
0#
#282
b0 $
b0 (
b10 '
b10 )
#285
1#
#290
0#
#292
1&
#295
b1 0
1#
#300
0#
#302
0&
#305
b11 0
b0 !
b0 .
1#
#310
0#
#315
b1 /
b10 !
b10 .
1#
#317
1"
#320
0#
#325
b0 0
1#
#327
0"
